{
  "pages": [
    {
      "elements": [
        {
          "type": "frame",
          "text": "Frame undefined",
          "width": "1061.71px",
          "height": "790.487px",
          "children": [],
          "style": {
            "order": null,
            "opacity": 1,
            "animationName": "",
            "animationDuration": "1s",
            "shadow": "",
            "background": "rgb(176, 224, 94)"
          },
          "config": {
            "name": "shape-rectangle",
            "clipPath": "M0,0L343.83498277892903,0L343.83498277892903,256L0,256Z"
          },
          "tooltip": {
            "enabled": false
          },
          "x": -217.782,
          "y": 492.832,
          "rotate": 21.356884184909326,
          "id": "73c90d27-13a8-4b53-8d66-84197fe5db5d"
        },
        {
          "type": "frame",
          "text": "Frame undefined",
          "width": "416.763px",
          "height": "416.75px",
          "children": [
            {
              "type": "image",
              "text": "Image",
              "width": "100%",
              "height": "100%",
              "style": {
                "order": null,
                "opacity": 1,
                "animationName": "",
                "animationDuration": "1s",
                "shadow": "",
                "borderWidth": 0,
                "borderColor": "#000000",
                "borderRadius": 0
              },
              "config": {
                "src": "https://media-public.canva.com/sRXDI/MAEH-esRXDI/1/s.jpg"
              },
              "x": 0,
              "y": 0,
              "rotate": 1.7763582409779452e-15,
              "id": "b0d80744-4615-4a8c-8900-d527e196bfbd",
              "frame": 0
            }
          ],
          "style": {
            "order": null,
            "opacity": 1,
            "animationName": "",
            "animationDuration": "1s",
            "shadow": "",
            "background": "rgba(0, 0, 0, 0)"
          },
          "config": {
            "name": "shape-circle",
            "clipPath": "M500.002000008,250.00300001200003C500.002000008,388.0685522742091 388.0705522822091,500 250.001000004,500C111.92944771779086,500 0,388.0685522742091 0,250.00300001200003C0,111.93044772179088 111.92944771779086,0 250.001000004,0C388.07255229020916,0 500.002000008,111.93044772179088 500.002000008,250.00300001200003Z"
          },
          "tooltip": {
            "enabled": false
          },
          "x": -17.188,
          "y": 205.569,
          "rotate": 1.7763582409779452e-15,
          "id": "2afa8d8e-39be-4bc7-8f7f-84632f08f31c"
        },
        {
          "type": "image",
          "text": "Image",
          "width": "493.538px",
          "height": "444.175px",
          "style": {
            "animationDuration": "1s",
            "animationName": "",
            "color": "#000000",
            "borderRadius": 0,
            "borderWidth": 0,
            "opacity": 1,
            "shadow": ""
          },
          "config": {
            "src": "blob:https://www.canva.com/07813c82-1c4d-46ac-9c56-5c418e3125fc"
          },
          "x": -133.084,
          "y": 330.94,
          "rotate": 0,
          "id": "b1291a10-b161-4356-85f5-ec195c13574c"
        },
        {
          "type": "frame",
          "text": "Frame undefined",
          "width": "346.25px",
          "height": "346.25px",
          "children": [
            {
              "type": "image",
              "text": "Happy mother washing baby clothes in machine",
              "width": "100%",
              "height": "100%",
              "style": {
                "order": null,
                "opacity": 1,
                "animationName": "",
                "animationDuration": "1s",
                "shadow": "",
                "borderWidth": 0,
                "borderColor": "#000000",
                "borderRadius": 0
              },
              "config": {
                "src": "https://media-public.canva.com/Wrk-Q/MAEZ-7Wrk-Q/1/s.jpg"
              },
              "x": 0,
              "y": 0,
              "rotate": 1.7763582409779452e-15,
              "id": "a1c4480c-77ec-4a11-95a0-2d61a026724c",
              "frame": 0
            }
          ],
          "style": {
            "order": null,
            "opacity": 1,
            "animationName": "",
            "animationDuration": "1s",
            "shadow": "",
            "background": "rgba(0, 0, 0, 0)"
          },
          "config": {
            "name": "shape-circle",
            "clipPath": "M500.002000008,250.00300001200003C500.002000008,388.0685522742091 388.0705522822091,500 250.001000004,500C111.92944771779086,500 0,388.0685522742091 0,250.00300001200003C0,111.93044772179088 111.92944771779086,0 250.001000004,0C388.07255229020916,0 500.002000008,111.93044772179088 500.002000008,250.00300001200003Z"
          },
          "tooltip": {
            "enabled": false
          },
          "x": 264.836,
          "y": 352.626,
          "rotate": 1.7763582409779452e-15,
          "id": "b0f1a5fd-4f7d-4385-aaf1-822cd7ebcde3"
        },
        {
          "type": "image",
          "text": "Image",
          "width": "384.725px",
          "height": "346.25px",
          "style": {
            "animationDuration": "1s",
            "animationName": "",
            "color": "#000000",
            "borderRadius": 0,
            "borderWidth": 0,
            "opacity": 1,
            "shadow": ""
          },
          "config": {
            "src": "blob:https://www.canva.com/07813c82-1c4d-46ac-9c56-5c418e3125fc"
          },
          "x": 259.562,
          "y": 348.06,
          "rotate": 0,
          "id": "42109395-1c3a-4c03-a7af-5f34c3dfdfdd"
        },
        {
          "type": "frame",
          "text": "Frame undefined",
          "width": "284.812px",
          "height": "284.812px",
          "children": [
            {
              "type": "image",
              "text": "People Inside Laundry Facility",
              "width": "100%",
              "height": "100%",
              "style": {
                "order": null,
                "opacity": 1,
                "animationName": "",
                "animationDuration": "1s",
                "shadow": "",
                "borderWidth": 0,
                "borderColor": "#000000",
                "borderRadius": 0
              },
              "config": {
                "src": "https://media-public.canva.com/Z6YqA/MAE7afZ6YqA/1/s.jpg"
              },
              "x": 0,
              "y": 0,
              "rotate": 1.7763582409779452e-15,
              "id": "683fa8d7-ef81-4ad6-ba9a-b7c723d0153b",
              "frame": 0
            }
          ],
          "style": {
            "order": null,
            "opacity": 1,
            "animationName": "",
            "animationDuration": "1s",
            "shadow": "",
            "background": "rgba(0, 0, 0, 0)"
          },
          "config": {
            "name": "shape-circle",
            "clipPath": "M500.002000008,250.00300001200003C500.002000008,388.0685522742091 388.0705522822091,500 250.001000004,500C111.92944771779086,500 0,388.0685522742091 0,250.00300001200003C0,111.93044772179088 111.92944771779086,0 250.001000004,0C388.07255229020916,0 500.002000008,111.93044772179088 500.002000008,250.00300001200003Z"
          },
          "tooltip": {
            "enabled": false
          },
          "x": 508.326,
          "y": 504.477,
          "rotate": 1.7763582409779452e-15,
          "id": "253e657b-2a4a-4dab-a181-1f302c33d79f"
        },
        {
          "type": "image",
          "text": "Image",
          "width": "340.5px",
          "height": "306.45px",
          "style": {
            "animationDuration": "1s",
            "animationName": "",
            "color": "#000000",
            "borderRadius": 0,
            "borderWidth": 0,
            "opacity": 1,
            "shadow": ""
          },
          "config": {
            "src": "blob:https://www.canva.com/07813c82-1c4d-46ac-9c56-5c418e3125fc"
          },
          "x": 488.836,
          "y": 493.658,
          "rotate": 0,
          "id": "49885dca-1951-48f1-a9b8-ede9bbbb4f92"
        },
        {
          "type": "frame",
          "text": "Frame rectangle",
          "width": "433.35px",
          "height": "92.6875px",
          "children": [],
          "style": {
            "order": null,
            "opacity": 1,
            "animationName": "",
            "animationDuration": "1s",
            "shadow": "",
            "background": "rgb(27, 27, 42)"
          },
          "config": {
            "name": "shape-round-rectangle",
            "clipPath": "M1044.4806402814215,0C1128.577692091308,0 1196.7518225576875,57.30755202165845 1196.7518225576875,128C1196.7518225576875,198.69244797834153 1128.577692091308,256 1044.4806402814215,256L152.27118227626588,256C68.17413046637924,256 0,198.6924479783416 0,128C0,57.30755202165848 68.17413046637921,0 152.27118227626588,0Z"
          },
          "tooltip": {
            "enabled": false
          },
          "x": -72.8957,
          "y": 675.339,
          "rotate": 0,
          "id": "55340b5a-290f-43ac-8354-e935e8f5c939"
        },
        {
          "type": "frame",
          "text": "Frame rectangle",
          "width": "664.525px",
          "height": "48.5px",
          "children": [],
          "style": {
            "order": null,
            "opacity": 1,
            "animationName": "",
            "animationDuration": "1s",
            "shadow": "",
            "background": "rgb(27, 27, 42)"
          },
          "config": {
            "name": "shape-round-rectangle",
            "clipPath": "M128.00000007195032,0L3378.841595979914,0C3449.5340438567964,0 3506.8415958555283,57.30755199873203 3506.8415958555283,128.00000007195032C3506.8415958555283,198.69244794883264 3449.5340438567964,255.99999994756465 3378.841595979914,255.99999994756465L128.00000007195032,255.99999994756465C57.30755199873203,255.99999994756465 0,198.69244794883264 0,128.00000007195032C0,57.30755199873203 57.30755199873203,0 128.00000007195032,0Z"
          },
          "tooltip": {
            "enabled": false
          },
          "x": 64.5856,
          "y": 993.134,
          "rotate": 0,
          "id": "0e1c1aee-a54c-4a16-9886-ed11e23705a8"
        },
        {
          "config": {
            "name": "123-456-7890123 Anywhere St., Any City"
          },
          "height": "40.175px",
          "id": "8d723b27-dc4f-49c1-a063-ae4ccb89adb1",
          "rotate": 0,
          "style": {
            "animationDuration": "1s",
            "animationName": "",
            "color": "rgb(255, 255, 255)",
            "fontSize": "16.3532px",
            "fontWeight": "400",
            "letterSpacing": "normal",
            "lineHeight": "22px",
            "opacity": 1,
            "shadow": "",
            "textAlign": "left",
            "textTransform": "none",
            "listStyleType": "none"
          },
          "text": "123-456-7890123 Anywhere St., Any City",
          "type": "text",
          "width": "634.95px",
          "x": 79.3701,
          "y": 997.298
        },
        {
          "type": "image",
          "text": "Image",
          "width": "26.1px",
          "height": "26.1px",
          "style": {
            "animationDuration": "1s",
            "animationName": "",
            "color": "#000000",
            "borderRadius": 0,
            "borderWidth": 0,
            "opacity": 1,
            "shadow": ""
          },
          "config": {
            "src": "blob:https://www.canva.com/8e9bf359-1af4-48ed-9b38-dbcc7a8b2838"
          },
          "x": 2.84217e-14,
          "y": 7.10543e-15,
          "rotate": 0,
          "id": "fd1df323-9e40-4eb5-b5e5-94657c061e7a"
        },
        {
          "config": {
            "name": "123-456-7890"
          },
          "height": "18.725px",
          "id": "3769db87-ee69-42c2-bee5-30b71cf88940",
          "rotate": 0,
          "style": {
            "animationDuration": "1s",
            "animationName": "",
            "color": "rgb(255, 255, 255)",
            "fontSize": "16.3532px",
            "fontWeight": "400",
            "letterSpacing": "normal",
            "lineHeight": "22px",
            "opacity": 1,
            "shadow": "",
            "textAlign": "left",
            "textTransform": "none",
            "listStyleType": "none"
          },
          "text": "123-456-7890",
          "type": "text",
          "width": "113.025px",
          "x": 33.1679,
          "y": 3.68789
        },
        {
          "type": "image",
          "text": "Image",
          "width": "26.1px",
          "height": "26.1px",
          "style": {
            "animationDuration": "1s",
            "animationName": "",
            "color": "#000000",
            "borderRadius": 0,
            "borderWidth": 0,
            "opacity": 1,
            "shadow": ""
          },
          "config": {
            "src": "blob:https://www.canva.com/d03f76e6-b036-417f-b0f9-7785f4bc039a"
          },
          "x": 164.484,
          "y": -3.19744e-14,
          "rotate": 0,
          "id": "b3558c08-a2bd-45aa-a8c2-d75758eb4ee1"
        },
        {
          "config": {
            "name": "123 Anywhere St., Any City"
          },
          "height": "18.725px",
          "id": "b6033bd7-1053-4946-89e4-62b4932b7723",
          "rotate": 0,
          "style": {
            "animationDuration": "1s",
            "animationName": "",
            "color": "rgb(255, 255, 255)",
            "fontSize": "16.3532px",
            "fontWeight": "400",
            "letterSpacing": "normal",
            "lineHeight": "22px",
            "opacity": 1,
            "shadow": "",
            "textAlign": "left",
            "textTransform": "none",
            "listStyleType": "none"
          },
          "text": "123 Anywhere St., Any City",
          "type": "text",
          "width": "214.85px",
          "x": 197.652,
          "y": 3.68789
        },
        {
          "type": "image",
          "text": "Image",
          "width": "167.275px",
          "height": "123.787px",
          "style": {
            "animationDuration": "1s",
            "animationName": "",
            "color": "#000000",
            "borderRadius": 0,
            "borderWidth": 0,
            "opacity": 1,
            "shadow": ""
          },
          "config": {
            "src": "https://media-public.canva.com/_Il3A/MADWDV_Il3A/2/t.png"
          },
          "x": 463.911,
          "y": 804.715,
          "rotate": 34.81735219459758,
          "id": "d854108b-d19f-4c1c-8a7c-893f09423f46"
        },
        {
          "type": "image",
          "text": "Image",
          "width": "164.387px",
          "height": "41.0875px",
          "style": {
            "animationDuration": "1s",
            "animationName": "",
            "color": "#000000",
            "borderRadius": 0,
            "borderWidth": 0,
            "opacity": 1,
            "shadow": ""
          },
          "config": {
            "src": "blob:https://www.canva.com/72b9b840-007f-4980-ac13-1a78656571ef"
          },
          "x": 22.6116,
          "y": 43.9396,
          "rotate": 0,
          "id": "0309cdb1-629a-4769-8a5b-8aaeb1294389"
        },
        {
          "config": {
            "name": "laundry"
          },
          "height": "91.9px",
          "id": "1aca39b2-6116-497a-86d2-8ee8d01e6c89",
          "rotate": 0,
          "style": {
            "animationDuration": "1s",
            "animationName": "",
            "color": "rgb(176, 224, 94)",
            "fontSize": "47.1006px",
            "fontWeight": "800",
            "letterSpacing": "1.13041px",
            "lineHeight": "65px",
            "opacity": 1,
            "shadow": "",
            "textAlign": "left",
            "textTransform": "uppercase",
            "listStyleType": "none"
          },
          "text": "laundry",
          "type": "text",
          "width": "450.987px",
          "x": 263.341,
          "y": 76.7717
        },
        {
          "config": {
            "name": "service"
          },
          "height": "92.1125px",
          "id": "f0e779bb-0f19-47cc-9df0-5589455d8216",
          "rotate": 0,
          "style": {
            "animationDuration": "1s",
            "animationName": "",
            "color": "rgb(176, 224, 94)",
            "fontSize": "42.6667px",
            "fontWeight": "800",
            "letterSpacing": "normal",
            "lineHeight": "59px",
            "opacity": 1,
            "shadow": "",
            "textAlign": "left",
            "textTransform": "uppercase",
            "listStyleType": "none"
          },
          "text": "service",
          "type": "text",
          "width": "374.987px",
          "x": 339.34,
          "y": 145.315
        },
        {
          "config": {
            "name": "list",
            "texts": [
              "Wash, Fold and Press",
              "Leather Cleaning",
              "Steam Cleaning",
              "Stain Removal"
            ],
            "type": "text"
          },
          "height": "33.975px",
          "id": "24df64a6-b3a5-4388-936c-2210e02e67b4",
          "rotate": 0,
          "style": {
            "animationDuration": "1s",
            "animationName": "",
            "color": "rgb(27, 27, 42)",
            "fontSize": "17.2446px",
            "fontWeight": "500",
            "letterSpacing": "normal",
            "lineHeight": "24px",
            "opacity": 1,
            "oder": null,
            "shadow": "",
            "textAlign": "left",
            "textTransform": "none",
            "listStyleType": "disc"
          },
          "text": "List",
          "type": "text",
          "width": "360.4px",
          "x": 83.1375,
          "y": 783.127
        },
        {
          "config": {
            "name": "Our Services"
          },
          "height": "47.1875px",
          "id": "bc7c65b5-85a8-4bf5-b443-ac38d319f5d9",
          "rotate": 0,
          "style": {
            "animationDuration": "1s",
            "animationName": "",
            "color": "rgb(176, 224, 94)",
            "fontSize": "25.9486px",
            "fontWeight": "500",
            "letterSpacing": "normal",
            "lineHeight": "36px",
            "opacity": 1,
            "shadow": "",
            "textAlign": "left",
            "textTransform": "none",
            "listStyleType": "none"
          },
          "text": "Our Services",
          "type": "text",
          "width": "263.8px",
          "x": 90.454,
          "y": 698.094
        },
        {
          "config": {
            "name": "Get Disc Up To 30% Off"
          },
          "height": "32.575px",
          "id": "50ba45ab-28b7-4c80-99c7-dbf6d4058f4b",
          "rotate": 0,
          "style": {
            "animationDuration": "1s",
            "animationName": "",
            "color": "rgb(255, 255, 255)",
            "fontSize": "17.4609px",
            "fontWeight": "400",
            "letterSpacing": "0.261913px",
            "lineHeight": "24px",
            "opacity": 1,
            "shadow": "",
            "textAlign": "left",
            "textTransform": "uppercase",
            "listStyleType": "none"
          },
          "text": "Get Disc Up To 30% Off",
          "type": "text",
          "width": "366.15px",
          "x": 348.187,
          "y": 223.599
        }
      ],
      "height": "1122.51px",
      "width": "793.7px",
      "id": "3731b701-a900-4509-b09d-33c6e2b43514",
      "title": "Untitled",
      "style": {
        "background": "rgb(27, 27, 42)"
      }
    }
  ]
}